querysh/__init__.py
querysh/cli.py
querysh/command.py
querysh/model.py
querysh/tests/conftest.py
querysh/tests/test_cli.py
querysh/tests/test_command.py
querysh/tests/test_model.py
querysh-0.1.9.dist-info/licenses/LICENSE
querysh-0.1.9.dist-info/METADATA
querysh-0.1.9.dist-info/WHEEL
querysh-0.1.9.dist-info/entry_points.txt
querysh-0.1.9.dist-info/top_level.txt
querysh-0.1.9.dist-info/RECORD
