Metadata-Version: 2.4
Name: querysh
Version: 0.1.9
Summary: A shell interface for MLX models
License: MIT
Requires-Python: >=3.8
License-File: LICENSE
Requires-Dist: mlx-lm>=0.0.6
Requires-Dist: rich>=13.7.0
Dynamic: license-file
Dynamic: requires-python
